MANIFEST.in
README.md
setup.py
bin/grandmasomsri-status
bin/grandpaprayud-status
bin/graph-power
grandmasomsri.egg-info/PKG-INFO
grandmasomsri.egg-info/SOURCES.txt
grandmasomsri.egg-info/dependency_links.txt
grandmasomsri.egg-info/requires.txt
grandmasomsri.egg-info/top_level.txt
src/grandmasomsri/grandmaSomsri.py
src/grandmasomsri/grandpaPrayud.py
src/grandmasomsri/graph/power.py