Metadata-Version: 1.0
Name: grandmasomsri
Version: 0.3
Summary: Grandma Somsri and Grandpa Prayud
Home-page: https://github.com/SOMSRICAT/grandmasomsri
Author: SomsriCat
Author-email: s.wuttiprasit@gmail.com
License: Somsri
Keywords: grandmasomsri grandpaprayud somsri prayud
Platform: UNKNOWN
